KungFu.py
setup.py
KungFuRunner-0.0.11.dist-info/LICENSE
KungFuRunner-0.0.11.dist-info/METADATA
KungFuRunner-0.0.11.dist-info/WHEEL
KungFuRunner-0.0.11.dist-info/top_level.txt
KungFuRunner-0.0.11.dist-info/RECORD
